README.md
setup.py
models/__init__.py
models/group.py
models/plugin.py
models/project.py
models/user.py
py_gerrit.egg-info/PKG-INFO
py_gerrit.egg-info/SOURCES.txt
py_gerrit.egg-info/dependency_links.txt
py_gerrit.egg-info/requires.txt
py_gerrit.egg-info/top_level.txt
utils/__init__.py
utils/jsonModel.py
utils/util.py