Metadata-Version: 1.1
Name: py-gerrit
Version: 1.0.2
Summary: gerrit简单封装
Home-page: https://github.com/youyan0704/py_gerrit
Author: allen.you
Author-email: youyan0704@163.com
License: UNKNOWN
Keywords: gerrit tools
Platform: UNKNOWN
Classifier: Programming Language :: Python :: 3.7
